CLASSIFIERS
HISTORY.rst
LICENSE.txt
MANIFEST.in
README.rst
setup.py
versioneer.py
djlimiter/__init__.py
djlimiter/_version.py
djlimiter/decorators.py
djlimiter/errors.py
djlimiter/middleware.py
djlimiter/util.py
djlimiter/version.py
djlimiter.egg-info/PKG-INFO
djlimiter.egg-info/SOURCES.txt
djlimiter.egg-info/dependency_links.txt
djlimiter.egg-info/not-zip-safe
djlimiter.egg-info/requires.txt
djlimiter.egg-info/top_level.txt
doc/Makefile
doc/source/api.rst
doc/source/conf.py
doc/source/config.rst
doc/source/decorators.rst
doc/source/index.rst
doc/source/recipes.rst
doc/source/strategy.rst
doc/source/string-notation.rst
requirements/ci.txt
requirements/main.txt
requirements/test.txt